{
    "id": 1242,
    "name": "L O W",
    "author": "ChaosDuCanada",
    "creators": ["ChaosDuCanada"],
    "verifier": "ChaosDuCanada",
    "verification": "",
    "percentToQualify": "64",
    "password": "Free To Copy",
    "records": [
        {
            "user": "Limabeanlimo",
            "link": "https://www.youtube.com/watch?v=bdicimt2RxU",
            "percent": 100,
            "hz": 60
        },
        {
            "user": "22knxwn",
            "link": "",
            "percent": 69,
            "hz": 240
        }
    ]
}
